cornice_sphinx/__init__.py
cornice_sphinx-0.4.dist-info/LICENSE
cornice_sphinx-0.4.dist-info/METADATA
cornice_sphinx-0.4.dist-info/WHEEL
cornice_sphinx-0.4.dist-info/top_level.txt
cornice_sphinx-0.4.dist-info/RECORD
