Metadata-Version: 2.1
Name: cornice-sphinx
Version: 0.4
Summary: Generate Sphinx documentation from a Cornice application
Home-page: https://github.com/Cornices/cornice.ext.sphinx
Author: Mozilla Services and contributors
Author-email: services-dev@mozilla.org
License: Apache License (2.0)
Keywords: web services
Classifier: Programming Language :: Python
Classifier: License :: OSI Approved :: Apache Software License
License-File: LICENSE
Requires-Dist: cornice
Requires-Dist: Sphinx
Requires-Dist: docutils
